luminaweaver/__init__.py
luminaweaver/main.py
luminaweaver/prompts.py
luminaweaver-2025.12.21140209.dist-info/METADATA
luminaweaver-2025.12.21140209.dist-info/WHEEL
luminaweaver-2025.12.21140209.dist-info/top_level.txt
luminaweaver-2025.12.21140209.dist-info/RECORD
