Metadata-Version: 2.4
Name: luminaweaver
Version: 2025.12.21140209
Summary: A new package that processes user-submitted text descriptions of images or videos containing watermarks and returns structured, watermark-free descriptions. It uses an LLM to reinterpret the content w
Author-email: luminaweaver <hi@eugene.plus>
License: MIT
Project-URL: Homepage, https://github.com/chigwell/luminaweaver
Requires-Python: >=3.9
Requires-Dist: langchain-llm7>=0.0.0
Requires-Dist: llmatch-messages>=0.0.0
Requires-Dist: langchain-core>=0.3.0
